<?xml version="1.0" encoding="utf-8"?>
<publishData>
  <publishProfile publishUrl="D:\Publicacion de Proyectos\ESM\Entrega 290911 1124" deleteExistingFiles="True" ftpAnonymousLogin="False" ftpPassiveMode="True" msdeploySite="" msdeploySiteID="" msdeployRemoteSitePhysicalPath="" msdeployAllowUntrustedCertificate="False" msdeploySkipExtraFilesOnServer="True" msdeployMarkAsApp="False" profileName="Juan Camilo Martinez MG" publishMethod="FileSystem" replaceMatchingFiles="False" userName="" savePWD="False" userPWD="" SelectedForPublish="True">
    <file relUrl="AmCharts/flash/amcolumn.swf" publishTime="08/27/2011 19:03:14" />
    <file relUrl="Icons/EducalidadHeader.png" publishTime="08/27/2011 19:02:49" />
    <file relUrl="Style/images/ui-icons_ffffff_256x240.png" publishTime="08/27/2011 19:02:29" />
    <file relUrl="Icons/Up.png" publishTime="08/27/2011 19:02:49" />
    <file relUrl="DynamicData/EntityTemplates/Default.ascx" publishTime="08/27/2011 19:02:51" />
    <file relUrl="Pretty/images/thumbnails/t_1.jpg" publishTime="08/27/2011 19:03:06" />
    <file relUrl="Icons/Window.png" publishTime="08/27/2011 19:02:49" />
    <file relUrl="DynamicData/PageTemplates/Insert.aspx" publishTime="08/29/2011 16:06:10" />
    <file relUrl="plupload/js/plupload.full.js" publishTime="09/01/2011 17:57:11" />
    <file relUrl="plupload/jquery.ui.plupload/img/plupload-bw.png" publishTime="09/01/2011 17:58:34" />
    <file relUrl="Scripts/full_calendar/fullcalendar.min.js" publishTime="09/05/2011 10:08:17" />
    <file relUrl="Icons/poll.png" publishTime="09/06/2011 18:57:50" />
    <file relUrl="Style/images/ui-bg_diagonals-small_50_0790c5_40x40.png" publishTime="08/27/2011 19:02:29" />
    <file relUrl="DynamicData/FieldTemplates/Children_Insert.ascx" publishTime="08/27/2011 19:02:50" />
    <file relUrl="web.config" publishTime="09/12/2011 12:50:29" />
    <file relUrl="plupload/jquery.plupload.queue/css/jquery.plupload.queue.css" publishTime="09/01/2011 17:58:33" />
    <file relUrl="AmCharts/flash/fonts/garamond.swf" publishTime="08/27/2011 19:03:13" />
    <file relUrl="DynamicData/Content/Images/PgFirst.gif" publishTime="08/27/2011 19:02:51" />
    <file relUrl="Icons/Chat.png" publishTime="08/27/2011 19:02:49" />
    <file relUrl="DynamicData/FieldTemplates/ForeignKey_Edit.ascx" publishTime="08/27/2011 19:02:50" />
    <file relUrl="DynamicData/Content/GridViewPager.ascx" publishTime="08/27/2011 19:02:51" />
    <file relUrl="Pretty/images/prettyPhoto/light_rounded/default_thumbnail.gif" publishTime="08/27/2011 19:02:53" />
    <file relUrl="DynamicData/FieldTemplates/Children.ascx" publishTime="08/27/2011 19:02:50" />
    <file relUrl="Icons/Home.png" publishTime="08/27/2011 19:02:49" />
    <file relUrl="Pretty/images/prettyPhoto/dark_square/sprite.png" publishTime="08/27/2011 19:02:53" />
    <file relUrl="Pretty/images/thumbnails/t_2.jpg" publishTime="08/27/2011 19:03:06" />
    <file relUrl="AmCharts/flash/swfobject.js" publishTime="08/27/2011 19:03:14" />
    <file relUrl="DynamicData/web.config" publishTime="08/27/2011 19:02:52" />
    <file relUrl="DynamicData/FieldTemplates/Text.ascx" publishTime="08/27/2011 19:02:50" />
    <file relUrl="plupload/js/plupload.html4.js" publishTime="09/01/2011 17:57:11" />
    <file relUrl="Pretty/css/prettyPhoto.css" publishTime="08/27/2011 19:03:07" />
    <file relUrl="Style/images/ui-icons_454545_256x240.png" publishTime="08/27/2011 19:02:29" />
    <file relUrl="Icons/Favorite.png" publishTime="08/27/2011 19:02:49" />
    <file relUrl="Pretty/images/fullscreen/2.jpg" publishTime="08/27/2011 19:03:06" />
    <file relUrl="Icons/Help.png" publishTime="08/27/2011 19:02:49" />
    <file relUrl="ModuloDocumentosSE.aspx" publishTime="09/13/2011 21:39:14" />
    <file relUrl="Pretty/images/prettyPhoto/light_square/default_thumbnail.gif" publishTime="08/27/2011 19:02:53" />
    <file relUrl="plupload/js/plupload.browserplus.js" publishTime="09/01/2011 17:57:11" />
    <file relUrl="Icons/Wizard.png" publishTime="08/27/2011 19:02:48" />
    <file relUrl="ActaVisitaEE.aspx" publishTime="09/29/2011 11:02:24" />
    <file relUrl="plupload/jquery.ui.plupload/jquery.ui.plupload.js" publishTime="09/01/2011 17:58:34" />
    <file relUrl="Icons/Folder_Open.png" publishTime="08/27/2011 19:02:49" />
    <file relUrl="Icons/Security.png" publishTime="08/27/2011 19:02:49" />
    <file relUrl="DynamicData/FieldTemplates/DateTime.ascx" publishTime="08/27/2011 19:02:50" />
    <file relUrl="AmCharts/flash/expressInstall.swf" publishTime="08/27/2011 19:03:14" />
    <file relUrl="Icons/Undo.png" publishTime="08/27/2011 19:02:49" />
    <file relUrl="bin/AjaxControlToolkit.dll" publishTime="08/27/2011 19:02:44" />
    <file relUrl="Pretty/images/prettyPhoto/facebook/contentPatternLeft.png" publishTime="08/27/2011 19:02:54" />
    <file relUrl="DynamicData/PageTemplates/Edit.aspx" publishTime="08/27/2011 19:02:51" />
    <file relUrl="plupload/js/plupload.js" publishTime="09/01/2011 17:57:11" />
    <file relUrl="Icons/unicef.png" publishTime="08/27/2011 19:02:49" />
    <file relUrl="Pretty/images/prettyPhoto/facebook/btnPrevious.png" publishTime="08/27/2011 19:02:54" />
    <file relUrl="plupload/jquery.plupload.queue/jquery.plupload.queue.js" publishTime="09/01/2011 17:58:34" />
    <file relUrl="DynamicData/FieldTemplates/Url.ascx" publishTime="08/27/2011 19:02:50" />
    <file relUrl="Style/images/ui-icons_72a03b_256x240.png" publishTime="08/27/2011 19:02:29" />
    <file relUrl="AyudaPreguntas.aspx" publishTime="09/09/2011 11:18:37" />
    <file relUrl="Pretty/js/jquery-1.3.2.min.js" publishTime="08/27/2011 19:03:07" />
    <file relUrl="plupload/jquery.plupload.queue/img/throbber.gif" publishTime="09/01/2011 17:58:34" />
    <file relUrl="Icons/Options.png" publishTime="08/27/2011 19:02:49" />
    <file relUrl="Pretty/images/prettyPhoto/light_square/btnNext.png" publishTime="08/27/2011 19:02:53" />
    <file relUrl="DynamicData/FieldTemplates/DateTime_Edit.ascx" publishTime="08/27/2011 19:02:50" />
    <file relUrl="DynamicData/PageTemplates/ListDetails.aspx" publishTime="08/27/2011 19:02:51" />
    <file relUrl="DynamicData/FieldTemplates/Integer_Edit.ascx" publishTime="08/27/2011 19:02:50" />
    <file relUrl="Icons/Burn.png" publishTime="08/27/2011 19:02:49" />
    <file relUrl="DynamicData/Filters/Boolean.ascx" publishTime="08/27/2011 19:02:50" />
    <file relUrl="AmCharts/javascript/images/lens.png" publishTime="08/27/2011 19:03:10" />
    <file relUrl="plupload/js/plupload.flash.swf" publishTime="09/01/2011 17:58:17" />
    <file relUrl="DynamicData/FieldTemplates/Enumeration.ascx" publishTime="08/27/2011 19:02:50" />
    <file relUrl="AmCharts/flash/patterns/vertical.swf" publishTime="08/27/2011 19:03:11" />
    <file relUrl="Icons/EE.png" publishTime="09/02/2011 19:42:02" />
    <file relUrl="DynamicData/FieldTemplates/Text_Edit.ascx" publishTime="08/27/2011 19:02:50" />
    <file relUrl="Icons/Paste.png" publishTime="08/27/2011 19:02:49" />
    <file relUrl="Evaluacion.aspx" publishTime="09/27/2011 15:16:58" />
    <file relUrl="Icons/LOGO CISP.png" publishTime="08/27/2011 19:02:49" />
    <file relUrl="Pretty/images/prettyPhoto/default/sprite.png" publishTime="08/27/2011 19:02:53" />
    <file relUrl="Icons/Mail_Read.png" publishTime="08/27/2011 19:02:49" />
    <file relUrl="Icons/added.png" publishTime="08/29/2011 15:31:22" />
    <file relUrl="Pretty/images/prettyPhoto/dark_square/default_thumbnail.gif" publishTime="08/27/2011 19:02:53" />
    <file relUrl="Pretty/images/fullscreen/6.jpg" publishTime="08/27/2011 19:03:06" />
    <file relUrl="mastercustom.css" publishTime="09/07/2011 14:44:20" />
    <file relUrl="DynamicData/Filters/Enumeration.ascx" publishTime="08/27/2011 19:02:50" />
    <file relUrl="DynamicData/Content/Images/PgLast.gif" publishTime="08/27/2011 19:02:51" />
    <file relUrl="Icons/Back.png" publishTime="08/27/2011 19:02:49" />
    <file relUrl="DynamicData/Filters/ForeignKey.ascx" publishTime="08/27/2011 19:02:50" />
    <file relUrl="Icons/Announcement.png" publishTime="08/27/2011 19:02:49" />
    <file relUrl="Icons/certificate.png" publishTime="09/06/2011 19:04:15" />
    <file relUrl="Pretty/images/prettyPhoto/dark_square/loader.gif" publishTime="08/27/2011 19:02:53" />
    <file relUrl="Icons/nav.png" publishTime="08/29/2011 12:11:26" />
    <file relUrl="Icons/Info.png" publishTime="08/27/2011 19:02:49" />
    <file relUrl="plupload/jquery.plupload.queue/img/error.gif" publishTime="09/01/2011 17:58:34" />
    <file relUrl="Pretty/images/prettyPhoto/light_square/btnPrevious.png" publishTime="08/27/2011 19:02:53" />
    <file relUrl="DynamicData/Content/Images/header_back.gif" publishTime="08/27/2011 19:02:51" />
    <file relUrl="AmCharts/flash/export.aspx" publishTime="08/27/2011 19:03:14" />
    <file relUrl="DynamicData/FieldTemplates/MultilineText_Edit.ascx" publishTime="08/27/2011 19:02:50" />
    <file relUrl="Icons/Folder.png" publishTime="08/27/2011 19:02:49" />
    <file relUrl="Icons/Alert.png" publishTime="08/27/2011 19:02:49" />
    <file relUrl="Icons/Stats.png" publishTime="08/27/2011 19:02:49" />
    <file relUrl="Pretty/js/jquery.prettyPhoto.js" publishTime="08/27/2011 19:03:07" />
    <file relUrl="Pretty/images/prettyPhoto/facebook/default_thumbnail.gif" publishTime="08/27/2011 19:02:54" />
    <file relUrl="DynamicData/FieldTemplates/Enumeration_Edit.ascx" publishTime="08/27/2011 19:02:50" />
    <file relUrl="Style/images/ui-bg_diagonals-small_0_0790c5_40x40.png" publishTime="08/27/2011 19:02:29" />
    <file relUrl="DynamicData/Content/Images/PgNext.gif" publishTime="08/27/2011 19:02:51" />
    <file relUrl="Pretty/images/prettyPhoto/facebook/contentPatternTop.png" publishTime="08/27/2011 19:02:54" />
    <file relUrl="Icons/Flag.png" publishTime="08/27/2011 19:02:49" />
    <file relUrl="AmCharts/javascript/raphael.js" publishTime="08/27/2011 19:03:11" />
    <file relUrl="Icons/Box.png" publishTime="08/27/2011 19:02:49" />
    <file relUrl="Icons/Key.png" publishTime="08/27/2011 19:02:49" />
    <file relUrl="Style/images/ui-bg_highlight-soft_100_f6f6f6_1x100.png" publishTime="08/27/2011 19:02:29" />
    <file relUrl="DynamicData/FieldTemplates/Decimal_Edit.ascx" publishTime="08/27/2011 19:02:50" />
    <file relUrl="Icons/1314381320_help_48.png" publishTime="08/27/2011 19:02:48" />
    <file relUrl="Pretty/images/fullscreen/4.jpg" publishTime="08/27/2011 19:03:06" />
    <file relUrl="Pretty/images/prettyPhoto/default/sprite_next.png" publishTime="08/27/2011 19:02:53" />
    <file relUrl="Pretty/images/fullscreen/1.jpg" publishTime="08/27/2011 19:03:06" />
    <file relUrl="Pretty/images/prettyPhoto/dark_square/btnPrevious.png" publishTime="08/27/2011 19:02:53" />
    <file relUrl="Pretty/images/fullscreen/5.jpg" publishTime="08/27/2011 19:03:06" />
    <file relUrl="AmCharts/flash/amradar.swf" publishTime="08/27/2011 19:03:14" />
    <file relUrl="plupload/jquery.ui.plupload/img/plupload.png" publishTime="09/01/2011 17:58:34" />
    <file relUrl="Consolidado.aspx" publishTime="09/01/2011 08:46:27" />
    <file relUrl="plupload/js/plupload.gears.js" publishTime="09/01/2011 17:57:11" />
    <file relUrl="AmCharts/flash/amcharts_key.txt" publishTime="08/27/2011 19:03:14" />
    <file relUrl="Icons/Forward.png" publishTime="08/27/2011 19:02:49" />
    <file relUrl="Pretty/images/prettyPhoto/light_rounded/btnPrevious.png" publishTime="08/27/2011 19:02:53" />
    <file relUrl="DynamicData/PageTemplates/List.aspx" publishTime="08/29/2011 16:01:09" />
    <file relUrl="plupload/js/plupload.html5.js" publishTime="09/01/2011 17:57:11" />
    <file relUrl="Pretty/images/prettyPhoto/facebook/sprite.png" publishTime="08/27/2011 19:02:54" />
    <file relUrl="Pretty/images/fullscreen/high.gif" publishTime="08/27/2011 19:03:06" />
    <file relUrl="Icons/progres.gif" publishTime="09/07/2011 16:50:17" />
    <file relUrl="Pretty/images/thumbnails/t_3.jpg" publishTime="08/27/2011 19:03:06" />
    <file relUrl="json.aspx" publishTime="09/05/2011 10:40:47" />
    <file relUrl="Icons/Address_Book.png" publishTime="08/27/2011 19:02:49" />
    <file relUrl="bin/ESM.dll" publishTime="09/29/2011 11:25:12" />
    <file relUrl="plupload/js/plupload.silverlight.js" publishTime="09/01/2011 17:57:11" />
    <file relUrl="Style/images/ui-bg_flat_0_aaaaaa_40x100.png" publishTime="08/27/2011 19:02:29" />
    <file relUrl="Pretty/js/jquery-1.4.4.min.js" publishTime="08/27/2011 19:03:07" />
    <file relUrl="Pretty/images/prettyPhoto/light_rounded/sprite.png" publishTime="08/27/2011 19:02:53" />
    <file relUrl="DynamicData/Content/Images/plus.gif" publishTime="08/27/2011 19:02:51" />
    <file relUrl="Scripts/ScrollTo/jquery.scrollTo-min.js" publishTime="09/06/2011 12:52:14" />
    <file relUrl="Icons/Tutorial.png" publishTime="08/27/2011 19:02:49" />
    <file relUrl="Default.aspx" publishTime="09/10/2011 11:59:41" />
    <file relUrl="Icons/Write.png" publishTime="08/27/2011 19:02:49" />
    <file relUrl="Pretty/images/prettyPhoto/light_rounded/btnNext.png" publishTime="08/27/2011 19:02:53" />
    <file relUrl="Icons/ok.png" publishTime="08/27/2011 19:02:49" />
    <file relUrl="Icons/Lock.png" publishTime="08/27/2011 19:02:49" />
    <file relUrl="Icons/clip_image002.jpg" publishTime="08/27/2011 19:02:49" />
    <file relUrl="AmCharts/javascript/amfallback.js" publishTime="08/27/2011 19:03:11" />
    <file relUrl="AmCharts/flash/fonts/times new roman.swf" publishTime="08/27/2011 19:03:13" />
    <file relUrl="Icons/Down.png" publishTime="08/27/2011 19:02:49" />
    <file relUrl="Scripts/jquery-1.6.3-vsdoc.js" publishTime="09/12/2011 10:48:08" />
    <file relUrl="Pretty/images/prettyPhoto/dark_square/contentPattern.png" publishTime="08/27/2011 19:02:53" />
    <file relUrl="Scripts/jquery-1.4.1.js" publishTime="08/27/2011 19:03:10" />
    <file relUrl="Icons/Web.png" publishTime="08/27/2011 19:02:49" />
    <file relUrl="Scripts/jquery-1.6.2.min.js" publishTime="08/27/2011 19:03:10" />
    <file relUrl="Icons/MENHeader.png" publishTime="08/27/2011 19:02:49" />
    <file relUrl="Pretty/images/prettyPhoto/dark_rounded/loader.gif" publishTime="08/27/2011 19:02:52" />
    <file relUrl="AmCharts/flash/ampie.swf" publishTime="08/27/2011 19:03:14" />
    <file relUrl="Icons/Stop.png" publishTime="08/27/2011 19:02:49" />
    <file relUrl="Pretty/images/prettyPhoto/default/sprite_y.png" publishTime="08/27/2011 19:02:53" />
    <file relUrl="AmCharts/flash/patterns/horizontal.swf" publishTime="08/27/2011 19:03:11" />
    <file relUrl="Icons/Refresh.png" publishTime="08/27/2011 19:02:49" />
    <file relUrl="ActaVisitaSE.aspx" publishTime="09/29/2011 10:00:21" />
    <file relUrl="plupload/jquery.plupload.queue/img/delete.gif" publishTime="09/01/2011 17:58:33" />
    <file relUrl="Icons/Bin_Empty.png" publishTime="08/27/2011 19:02:49" />
    <file relUrl="Icons/Close.png" publishTime="08/27/2011 19:02:49" />
    <file relUrl="Icons/upload.png" publishTime="09/02/2011 12:43:48" />
    <file relUrl="Style/images/ui-icons_0073ea_256x240.png" publishTime="08/27/2011 19:02:29" />
    <file relUrl="LecturaContextoSE.aspx" publishTime="09/29/2011 09:29:41" />
    <file relUrl="plupload/jquery.plupload.queue/img/backgrounds.gif" publishTime="09/01/2011 17:58:33" />
    <file relUrl="Style/images/ui-bg_flat_55_ffffff_40x100.png" publishTime="08/27/2011 19:02:29" />
    <file relUrl="plupload/jquery.plupload.queue/img/done.gif" publishTime="09/01/2011 17:58:33" />
    <file relUrl="Pretty/js/jquery-1.6.1.min.js" publishTime="08/27/2011 19:03:07" />
    <file relUrl="MenuEvaluacion.aspx" publishTime="09/28/2011 02:52:06" />
    <file relUrl="Global.asax" publishTime="08/27/2011 19:04:05" />
    <file relUrl="Style/images/ui-icons_ff0084_256x240.png" publishTime="08/27/2011 19:02:29" />
    <file relUrl="Icons/SE.png" publishTime="09/02/2011 19:52:15" />
    <file relUrl="Pretty/images/prettyPhoto/dark_rounded/contentPattern.png" publishTime="08/27/2011 19:02:52" />
    <file relUrl="Style/jquery-ui-1.8.15.custom.css" publishTime="08/27/2011 19:02:29" />
    <file relUrl="Icons/cancel.png" publishTime="08/29/2011 15:31:29" />
    <file relUrl="Icons/Tip.png" publishTime="08/27/2011 19:02:49" />
    <file relUrl="LecturaContextoEE.aspx" publishTime="09/28/2011 16:33:21" />
    <file relUrl="AmCharts/flash/amline.swf" publishTime="08/27/2011 19:03:14" />
    <file relUrl="Pretty/images/prettyPhoto/facebook/contentPatternRight.png" publishTime="08/27/2011 19:02:54" />
    <file relUrl="AmCharts/javascript/images/dragIcon.gif" publishTime="08/27/2011 19:03:10" />
    <file relUrl="Icons/Search.png" publishTime="08/27/2011 19:02:49" />
    <file relUrl="Icons/CD.png" publishTime="08/27/2011 19:02:49" />
    <file relUrl="Style/images/ui-bg_glass_65_ffffff_1x400.png" publishTime="08/27/2011 19:02:29" />
    <file relUrl="Icons/Computer.png" publishTime="08/27/2011 19:02:49" />
    <file relUrl="Pretty/images/prettyPhoto/dark_rounded/btnPrevious.png" publishTime="08/27/2011 19:02:52" />
    <file relUrl="Pretty/images/prettyPhoto/dark_rounded/sprite.png" publishTime="08/27/2011 19:02:52" />
    <file relUrl="DynamicData/PageTemplates/Details.aspx" publishTime="08/27/2011 19:02:51" />
    <file relUrl="ModuloDocumentos.aspx" publishTime="09/13/2011 21:39:29" />
    <file relUrl="AmCharts/flash/fonts/tahoma.swf" publishTime="08/27/2011 19:03:13" />
    <file relUrl="Icons/EducalidadFooter.png" publishTime="08/27/2011 19:02:49" />
    <file relUrl="Scripts/full_calendar/gcal.js" publishTime="09/05/2011 10:08:18" />
    <file relUrl="Style/images/ui-bg_flat_75_ffffff_40x100.png" publishTime="08/27/2011 19:02:29" />
    <file relUrl="Scripts/jquery-1.4.1.min.js" publishTime="08/27/2011 19:03:10" />
    <file relUrl="Style/images/ui-bg_diagonals-small_25_72a03b_40x40.png" publishTime="08/27/2011 19:02:29" />
    <file relUrl="Pretty/images/prettyPhoto/dark_square/btnNext.png" publishTime="08/27/2011 19:02:53" />
    <file relUrl="Icons/Pictures.png" publishTime="08/27/2011 19:02:49" />
    <file relUrl="Icons/MENFooter.png" publishTime="08/27/2011 19:02:49" />
    <file relUrl="Pretty/images/prettyPhoto/default/loader.gif" publishTime="08/27/2011 19:02:53" />
    <file relUrl="Pretty/images/prettyPhoto/light_rounded/loader.gif" publishTime="08/27/2011 19:02:53" />
    <file relUrl="Icons/Clock.png" publishTime="08/27/2011 19:02:49" />
    <file relUrl="Pretty/images/thumbnails/quicktime-logo.gif" publishTime="08/27/2011 19:03:06" />
    <file relUrl="plupload/jquery.plupload.queue/img/buttons.png" publishTime="09/01/2011 17:58:33" />
    <file relUrl="plupload/jquery.plupload.queue/img/transp50.png" publishTime="09/01/2011 17:58:34" />
    <file relUrl="Pretty/images/prettyPhoto/light_square/loader.gif" publishTime="08/27/2011 19:02:53" />
    <file relUrl="Icons/Stationery.png" publishTime="08/27/2011 19:02:49" />
    <file relUrl="Pretty/images/prettyPhoto/facebook/loader.gif" publishTime="08/27/2011 19:02:54" />
    <file relUrl="Pretty/images/prettyPhoto/default/sprite_x.png" publishTime="08/27/2011 19:02:53" />
    <file relUrl="AmCharts/flash/plugins/value_indicator.swf" publishTime="08/27/2011 19:03:12" />
    <file relUrl="Style/images/ui-icons_666666_256x240.png" publishTime="08/27/2011 19:02:29" />
    <file relUrl="Pretty/images/thumbnails/t_4.jpg" publishTime="08/27/2011 19:03:06" />
    <file relUrl="Icons/Contact.png" publishTime="08/27/2011 19:02:49" />
    <file relUrl="Pretty/images/fullscreen/huge.gif" publishTime="08/27/2011 19:03:06" />
    <file relUrl="DynamicData/Content/Images/Back.gif" publishTime="08/27/2011 19:02:51" />
    <file relUrl="DynamicData/EntityTemplates/Default_Insert.ascx" publishTime="08/27/2011 19:02:51" />
    <file relUrl="Citas.aspx" publishTime="09/28/2011 12:47:58" />
    <file relUrl="Scripts/full_calendar/fullcalendar.js" publishTime="09/05/2011 10:08:17" />
    <file relUrl="Pretty/images/prettyPhoto/default/default_thumb.png" publishTime="08/27/2011 19:02:53" />
    <file relUrl="DynamicData/FieldTemplates/Boolean_Edit.ascx" publishTime="08/27/2011 19:02:50" />
    <file relUrl="DynamicData/EntityTemplates/Default_Edit.ascx" publishTime="08/27/2011 19:02:51" />
    <file relUrl="Pretty/images/fullscreen/3.jpg" publishTime="08/27/2011 19:03:06" />
    <file relUrl="Pretty/images/thumbnails/flash-logo.png" publishTime="08/27/2011 19:03:06" />
    <file relUrl="Site.master" publishTime="09/29/2011 11:13:05" />
    <file relUrl="AmCharts/flash/amxy.swf" publishTime="08/27/2011 19:03:14" />
    <file relUrl="Scripts/jquery-1.4.1-vsdoc.js" publishTime="08/27/2011 19:03:09" />
    <file relUrl="DynamicData/FieldTemplates/EmailAddress.ascx" publishTime="08/27/2011 19:02:50" />
    <file relUrl="Pretty/images/thumbnails/t_5.jpg" publishTime="08/27/2011 19:03:06" />
    <file relUrl="Icons/Add.png" publishTime="08/27/2011 19:02:49" />
    <file relUrl="bin/ESM.pdb" publishTime="09/29/2011 11:25:10" />
    <file relUrl="Pretty/images/prettyPhoto/dark_rounded/btnNext.png" publishTime="08/27/2011 19:02:52" />
    <file relUrl="Icons/Portfolio.png" publishTime="08/27/2011 19:02:49" />
    <file relUrl="Icons/RSS.png" publishTime="08/27/2011 19:02:49" />
    <file relUrl="Pretty/images/prettyPhoto/facebook/btnNext.png" publishTime="08/27/2011 19:02:54" />
    <file relUrl="Icons/ProsperidadTodosFooter.png" publishTime="08/27/2011 19:02:48" />
    <file relUrl="Icons/Database.png" publishTime="08/27/2011 19:02:49" />
    <file relUrl="Icons/Edit.png" publishTime="08/27/2011 19:02:49" />
    <file relUrl="Icons/1314641093_plus_48.png" publishTime="08/29/2011 13:04:57" />
    <file relUrl="Login.aspx" publishTime="09/23/2011 09:17:21" />
    <file relUrl="Scripts/full_calendar/fullcalendar.print.css" publishTime="09/05/2011 10:08:17" />
    <file relUrl="Pretty/images/prettyPhoto/facebook/contentPatternBottom.png" publishTime="08/27/2011 19:02:54" />
    <file relUrl="plupload/js/plupload.flash.js" publishTime="09/01/2011 17:57:11" />
    <file relUrl="Icons/Mail.png" publishTime="08/27/2011 19:02:49" />
    <file relUrl="Icons/System.png" publishTime="08/27/2011 19:02:49" />
    <file relUrl="Scripts/ScrollTo/jquery.scrollTo.js" publishTime="09/06/2011 12:52:14" />
    <file relUrl="Pretty/images/prettyPhoto/light_square/sprite.png" publishTime="08/27/2011 19:02:53" />
    <file relUrl="DynamicData/FieldTemplates/ForeignKey.ascx" publishTime="08/27/2011 19:02:50" />
    <file relUrl="Icons/Delete.png" publishTime="08/27/2011 19:02:48" />
    <file relUrl="Pretty/images/fullscreen/wide.gif" publishTime="08/27/2011 19:03:06" />
    <file relUrl="Icons/User.png" publishTime="08/27/2011 19:02:49" />
    <file relUrl="Icons/Bin_Full.png" publishTime="08/27/2011 19:02:49" />
    <file relUrl="DynamicData/FieldTemplates/Boolean.ascx" publishTime="08/27/2011 19:02:50" />
    <file relUrl="Icons/Music.png" publishTime="08/27/2011 19:02:49" />
    <file relUrl="AmCharts/javascript/amcharts.js" publishTime="08/27/2011 19:03:11" />
    <file relUrl="Icons/Floppy.png" publishTime="08/27/2011 19:02:49" />
    <file relUrl="Icons/Calender.png" publishTime="08/27/2011 19:02:49" />
    <file relUrl="Ayuda.aspx" publishTime="09/13/2011 17:20:45" />
    <file relUrl="AmCharts/flash/fonts/arial.swf" publishTime="08/27/2011 19:03:13" />
    <file relUrl="plupload/jquery.plupload.queue/img/buttons-disabled.png" publishTime="09/01/2011 17:58:33" />
    <file relUrl="plupload/jquery.ui.plupload/css/jquery.ui.plupload.css" publishTime="09/01/2011 17:58:34" />
    <file relUrl="Icons/Template.png" publishTime="08/27/2011 19:02:49" />
    <file relUrl="Scripts/full_calendar/fullcalendar.css" publishTime="09/05/2011 10:08:17" />
    <file relUrl="Icons/Tag.png" publishTime="08/27/2011 19:02:49" />
    <file relUrl="Pretty/images/prettyPhoto/default/sprite_prev.png" publishTime="08/27/2011 19:02:53" />
    <file relUrl="Icons/Tools.png" publishTime="08/27/2011 19:02:49" />
    <file relUrl="AmCharts/flash/patterns/diagonal.swf" publishTime="08/27/2011 19:03:11" />
    <file relUrl="plupload/js/plupload.silverlight.xap" publishTime="09/01/2011 17:57:11" />
    <file relUrl="Scripts/jquery-ui-1.8.15.custom.min.js" publishTime="08/27/2011 19:03:10" />
    <file relUrl="Site.css" publishTime="08/29/2011 12:56:49" />
    <file relUrl="Pretty/images/prettyPhoto/dark_rounded/default_thumbnail.gif" publishTime="08/27/2011 19:02:52" />
    <file relUrl="Icons/Speaker.png" publishTime="08/27/2011 19:02:49" />
    <file relUrl="DynamicData/Content/Images/PgPrev.gif" publishTime="08/27/2011 19:02:51" />
    <file relUrl="Icons/Redo.png" publishTime="08/27/2011 19:02:49" />
  </publishProfile>
</publishData>